[
  {
    "title": "3丁目のタマ うちのタマ知りませんか?",
    "date": "1993-07-03",
    "bangumi": {
      "id": "8247"
    },
    "tmdb": {
      "id": 34758,
      "type": "tv",
      "search": {
        "adult": false,
        "backdrop_path": "/fbsMw9TGh7MUP1kahLA6hu14ytX.jpg",
        "genre_ids": [
          16,
          10762
        ],
        "id": 34758,
        "origin_country": [
          "JP"
        ],
        "original_language": "ja",
        "original_name": "3丁目のタマ うちのタマ知りませんか？",
        "overview": "Sony Creative Products的人气文具品牌“Tama & Friends”的衍生作品。故事围绕着一个住在三丁目的小男孩冈本武与他饲养的一只花猫圆圆所发生的生活小趣事，以及圆圆与它的朋友妙妙、百吉等宠物每天的历险故事。",
        "poster_path": "/g5x1jJ2xdLS51tvU40aOrn0zdBE.jpg",
        "first_air_date": "1993-07-03",
        "name": "淘气猫 喵喵三丁目"
      }
    }
  },
  {
    "title": "Dr.スランプ アラレちゃん んちゃ!ペンギン村より愛をこめて",
    "date": "1993-07-10",
    "bangumi": {
      "id": "82725"
    },
    "tmdb": {
      "id": 146092,
      "type": "movie",
      "search": {
        "adult": false,
        "backdrop_path": null,
        "genre_ids": [
          16,
          35
        ],
        "id": 146092,
        "original_language": "ja",
        "original_title": "Ｄｒ．スランプ アラレちゃん んちゃ！ペンギン村より愛をこめて",
        "overview": "Unable to entertain their princess Puruah, the kingdom of Yapaya requests professor Senbei to create a comedic robot capable of making her laugh for the first time in her life.",
        "poster_path": "/4NxmXijrStKvsuyarBWuR0WP14J.jpg",
        "release_date": "1993-07-10",
        "title": "阿拉蕾剧场版07 爱在天神村",
        "video": false
      }
    }
  },
  {
    "title": "ドラゴンボールZ 銀河ギリギリ!!ぶっちぎりの凄い奴",
    "date": "1993-07-10",
    "bangumi": {
      "id": "45394"
    },
    "tmdb": {
      "id": 39105,
      "type": "movie",
      "search": {
        "adult": false,
        "backdrop_path": "/iChtjY4jZTvYEG0lTSxT5B3nG1l.jpg",
        "genre_ids": [
          28,
          16,
          878
        ],
        "id": 39105,
        "original_language": "ja",
        "original_title": "ドラゴンボールZ 銀河ギリギリ!! ぶっちぎりの凄い奴",
        "overview": "人造人沙鲁战役过后，地球终于迎来了宝贵的和平，而骗子撒旦作为拯救了世界的英雄受到全人类的爱戴。世界首富钱多多为了给宝贝儿子庆生，出巨资举行了新一届的天下第一比武大会，成功晋级的选手有望和钱多多请来的四名所谓的外星人对决，最终获胜者还可以得到挑战撒旦的殊荣。此外，胜利者将得到一亿元奖金和环游世界的机会。超高的荣誉和报酬，连Z战士也坐不住了，纷纷报名参加。当然悟饭（野泽雅子 饰）、特兰克斯等人的出现，让撒旦心惊胆颤。一番较量过后，悟饭等人顺利晋级，但是等待他们的却是无比凶残和强大的宇宙人。意想不到的敌人，地球新的危机出现……",
        "poster_path": "/iihTK9Af8G1ZzBjkIIAV4qQMkzF.jpg",
        "release_date": "1993-07-10",
        "title": "龙珠Z剧场版9：银河面临危机!! 身手不凡的高手!!",
        "video": false
      }
    }
  },
  {
    "title": "幽☆遊☆白書",
    "date": "1993-07-10",
    "bangumi": {
      "id": "8805"
    },
    "tmdb": {
      "id": 45278,
      "type": "movie",
      "search": {
        "adult": false,
        "backdrop_path": "/EeMTDu5KxYHA53iFnaLPEHjN34.jpg",
        "genre_ids": [
          16,
          28,
          12,
          35
        ],
        "id": 45278,
        "original_language": "ja",
        "original_title": "幽遊白書",
        "overview": "浦饭幽助被灵界的阎王大人儿子小阎王赋予了一度失去的生命，他作为灵界侦探的任务是抓住潜入人类世界的灵界罪犯。在小阎王的指引下，幽助和他曾经的对手桑原，曾经是灵界罪犯的藏马，飞影一起并肩作战。  暑假到来，牡丹出现在桑原与幽助的面前，原来是小阎王被绑架了！犯人要求得到阎王大人的金印，有了金印，就可以在灵界为所欲为。为了救出小阎王并保护金印，幽助，桑原，藏马，飞影一行人在牡丹的指引下，前往了交易场所岩浆谷，展开了一场激烈的战斗！",
        "poster_path": "/cf6twiyA7XuJcVYgTtHwYDUQrjv.jpg",
        "release_date": "1993-07-10",
        "title": "幽游白书",
        "video": false
      }
    }
  },
  {
    "title": "それいけ!アンパンマン 恐竜ノッシーの大冒険",
    "date": "1993-07-17",
    "bangumi": {
      "id": "89701"
    },
    "tmdb": {
      "id": 361500,
      "type": "movie",
      "search": {
        "adult": false,
        "backdrop_path": "/sL3MwgR9Dhf99BUzggfsNm84fsR.jpg",
        "genre_ids": [
          10751,
          16
        ],
        "id": 361500,
        "original_language": "ja",
        "original_title": "それいけ! アンパンマン 恐竜ノッシーの大冒険",
        "overview": "Anpanman dinosaur 'Nessie' adventure. Will Anpanmen really be able to save the land of dinosaurs by defeating Baikinman and Gorongora?",
        "poster_path": "/1jqmGC5LxV5DHPCSTUTwSKbO8Gw.jpg",
        "release_date": "1993-07-17",
        "title": "面包超人:恐龙诺西历险记",
        "video": true
      }
    }
  },
  {
    "title": "ルパン三世 ルパン暗殺指令",
    "date": "1993-07-23",
    "bangumi": {
      "id": "84984"
    },
    "tmdb": {
      "id": 76190,
      "type": "movie",
      "search": {
        "adult": false,
        "backdrop_path": "/4zHScUX53WcxTVxR3ZwiKBQym38.jpg",
        "id": 76190,
        "title": "鲁邦三世：鲁邦暗杀指令",
        "original_language": "ja",
        "original_title": "ルパン三世 ルパン暗殺指令",
        "overview": "钱形被调职，不再负责鲁邦案子。继任者基斯得到的追捕命令是：“抓到鲁邦，不论死活”。于是国际刑警对鲁邦的追捕变成了暗杀……  　　本作为鲁邦三世第五部TVsp，1993年7月23日播送",
        "poster_path": "/y99HibIl6ICHoioDcAMHfLv3I87.jpg",
        "media_type": "movie",
        "genre_ids": [
          16,
          10770,
          28,
          35,
          80
        ],
        "release_date": "1999-05-04",
        "video": false
      }
    }
  },
  {
    "title": "クレヨンしんちゃん アクション仮面VSハイグレ魔王",
    "date": "1993-07-24",
    "bangumi": {
      "id": "8966"
    },
    "tmdb": {
      "id": 128868,
      "type": "movie",
      "search": {
        "adult": false,
        "backdrop_path": "/iGu27QGQtquhweyxXoVK4N6FkHs.jpg",
        "genre_ids": [
          16,
          35
        ],
        "id": 128868,
        "original_language": "ja",
        "original_title": "クレヨンしんちゃん アクション仮面VSハイグレ魔王",
        "overview": "动感超人的动感石头被泳装魔王抢走了，因而无法回到原来的世界，于是指派小新一家人成为动感战士前往另一个世界，这时另一个世界的人纷纷被变成泳装人，小新听了莉莉和博士的说明后，决定协助动感超人克服危机，他和动感超人能打败魔王挽救地球的和平吗...",
        "poster_path": "/d4pof1nNlhDP2VrZHDR1gBOUCrC.jpg",
        "release_date": "1993-07-24",
        "title": "蜡笔小新：动感超人大战泳装魔王",
        "video": false
      }
    }
  },
  {
    "title": "ろくでなしBLUES 1993",
    "date": "1993-07-24",
    "bangumi": {
      "id": "104006"
    },
    "tmdb": {
      "id": 461499,
      "type": "movie",
      "search": {
        "adult": false,
        "backdrop_path": "/8t5bLsNTjZaNWOxqUrHZMasfcZe.jpg",
        "genre_ids": [
          35,
          28,
          16,
          18
        ],
        "id": 461499,
        "original_language": "ja",
        "original_title": "ろくでなしBLUES 1993",
        "overview": "Taison Maeda's Teiken High School class goes on a field trip to the Kansai region of Japan, which is where Taison is from. Taison's little brother Youkou sent a message to Taison & his older brother Fujio that their father, Monson, is sick and that they should return home to visit him. This trip back will also allow Taison to put some closure on his past regarding his friend Naoto & his ex, Haruka.",
        "poster_path": "/fScTrblFtTlobzbEERhyhvDgOOL.jpg",
        "release_date": "1993-07-24",
        "title": "无赖布鲁斯",
        "video": false
      }
    }
  }
]