[
  {
    "title": "家族ロビンソン漂流記ふしぎな島のフローネ",
    "bangumi": {
      "date": "1981-01-04",
      "platform": "TV",
      "images": {
        "small": "https://lain.bgm.tv/r/200/pic/cover/l/e7/b9/23612_FA7jl.jpg",
        "grid": "https://lain.bgm.tv/r/100/pic/cover/l/e7/b9/23612_FA7jl.jpg",
        "large": "https://lain.bgm.tv/pic/cover/l/e7/b9/23612_FA7jl.jpg",
        "medium": "https://lain.bgm.tv/r/800/pic/cover/l/e7/b9/23612_FA7jl.jpg",
        "common": "https://lain.bgm.tv/r/400/pic/cover/l/e7/b9/23612_FA7jl.jpg"
      },
      "summary": "　　开朗有朝气的女孩子芙劳拉。她的家人在瑞士的伯恩做着医生。有一天得到了一封在澳大利亚的朋友寄给她家人的信，改变了这一家人的命运。澳大利亚那儿需要医生，所以芙劳拉一家就动身前往。\r\n　　但是，在一家人搭乘黑本大鹏鸟号（ブラックバーンロック号）这艘船不久之后，很不巧的船被卷入了暴风雨之中，结果发生了船难。所幸一家奇迹似的成员们都平安无事，不过一家却漂流到一处不知名的无人岛上。\r\n　　那个时候有感觉很绝望的时候，也有很悲哀的时候，但是在家族的人们互相勉励之后，决定开始携手度过难关。前半段是在无人岛上的生存生活，主要是以挖水井、开辟田地、建照树屋、盐、砂糖等等的民生必需品。\r\n　　而后半段，在一家得知无人岛的火山要爆发的时候，他们与新的漂流者莫顿和塔姆塔姆的协助制作了帆船，尝试着逃出那里。",
      "name": "家族ロビンソン漂流記ふしぎな島のフローネ",
      "name_cn": "鲁滨逊一家漂流记",
      "tags": [
        {
          "name": "世界名作剧场",
          "count": 5
        },
        {
          "name": "童年",
          "count": 4
        },
        {
          "name": "1981",
          "count": 2
        },
        {
          "name": "治愈系",
          "count": 2
        },
        {
          "name": "世界名作劇場",
          "count": 1
        }
      ],
      "infobox": [
        {
          "key": "中文名",
          "value": "鲁滨逊一家漂流记"
        },
        {
          "key": "别名",
          "value": [
            {
              "v": "家族鲁宾逊漂流记 不可思议之岛的芙劳拉"
            },
            {
              "v": "新鲁宾逊漂流记"
            },
            {
              "v": "Kazoku Robinson Hyouryuuki: Fushigi na Shima no Flone"
            },
            {
              "v": "Robinson Family Lost at Sea - Flone of the Marvelous Island"
            },
            {
              "v": "瑞士家庭漂流记"
            }
          ]
        },
        {
          "key": "话数",
          "value": "50"
        },
        {
          "key": "放送开始",
          "value": "1981年1月4日"
        },
        {
          "key": "播放结束",
          "value": "1981年12月27日"
        }
      ],
      "rating": {
        "rank": 0,
        "total": 8,
        "count": {
          "1": 0,
          "2": 0,
          "3": 0,
          "4": 1,
          "5": 0,
          "6": 3,
          "7": 3,
          "8": 1,
          "9": 0,
          "10": 0
        },
        "score": 6.4
      },
      "total_episodes": 50,
      "collection": {
        "on_hold": 4,
        "dropped": 5,
        "wish": 23,
        "collect": 15,
        "doing": 2
      },
      "id": 23612,
      "eps": 50,
      "volumes": 0,
      "locked": false,
      "nsfw": false,
      "type": 2,
      "relations": [
        {
          "images": {
            "small": "https://lain.bgm.tv/r/200/pic/cover/l/2b/52/316541_zBBJl.jpg",
            "grid": "https://lain.bgm.tv/r/100/pic/cover/l/2b/52/316541_zBBJl.jpg",
            "large": "https://lain.bgm.tv/pic/cover/l/2b/52/316541_zBBJl.jpg",
            "medium": "https://lain.bgm.tv/r/800/pic/cover/l/2b/52/316541_zBBJl.jpg",
            "common": "https://lain.bgm.tv/r/400/pic/cover/l/2b/52/316541_zBBJl.jpg"
          },
          "name": "世界名作劇場・完結版 家族ロビンソン漂流記 ふしぎな島のフローネ",
          "name_cn": "世界名作剧场·完结版 鲁滨逊一家漂流记",
          "relation": "总集篇",
          "type": 2,
          "id": 316541
        },
        {
          "images": {
            "small": "https://lain.bgm.tv/r/200/pic/cover/l/d6/25/448715_kmkKR.jpg",
            "grid": "https://lain.bgm.tv/r/100/pic/cover/l/d6/25/448715_kmkKR.jpg",
            "large": "https://lain.bgm.tv/pic/cover/l/d6/25/448715_kmkKR.jpg",
            "medium": "https://lain.bgm.tv/r/800/pic/cover/l/d6/25/448715_kmkKR.jpg",
            "common": "https://lain.bgm.tv/r/400/pic/cover/l/d6/25/448715_kmkKR.jpg"
          },
          "name": "裸足のフローネ / フローネの夢",
          "name_cn": "",
          "relation": "片头曲",
          "type": 3,
          "id": 448715
        },
        {
          "images": {
            "small": "https://lain.bgm.tv/r/200/pic/cover/l/17/35/448982_2PUzk.jpg",
            "grid": "https://lain.bgm.tv/r/100/pic/cover/l/17/35/448982_2PUzk.jpg",
            "large": "https://lain.bgm.tv/pic/cover/l/17/35/448982_2PUzk.jpg",
            "medium": "https://lain.bgm.tv/r/800/pic/cover/l/17/35/448982_2PUzk.jpg",
            "common": "https://lain.bgm.tv/r/400/pic/cover/l/17/35/448982_2PUzk.jpg"
          },
          "name": "あしたになれば / 風と唄おう",
          "name_cn": "",
          "relation": "插入歌",
          "type": 3,
          "id": 448982
        },
        {
          "images": {
            "small": "https://lain.bgm.tv/r/200/pic/cover/l/1a/55/448983_0G3hc.jpg",
            "grid": "https://lain.bgm.tv/r/100/pic/cover/l/1a/55/448983_0G3hc.jpg",
            "large": "https://lain.bgm.tv/pic/cover/l/1a/55/448983_0G3hc.jpg",
            "medium": "https://lain.bgm.tv/r/800/pic/cover/l/1a/55/448983_0G3hc.jpg",
            "common": "https://lain.bgm.tv/r/400/pic/cover/l/1a/55/448983_0G3hc.jpg"
          },
          "name": "星の子守唄 / こっちへおいでフローネ",
          "name_cn": "",
          "relation": "插入歌",
          "type": 3,
          "id": 448983
        }
      ]
    }
  },
  {
    "title": "最強ロボ ダイオージャ",
    "bangumi": {
      "date": "1981-01-31",
      "platform": "TV",
      "images": {
        "small": "https://lain.bgm.tv/r/200/pic/cover/l/72/2e/37287_NAOON.jpg",
        "grid": "https://lain.bgm.tv/r/100/pic/cover/l/72/2e/37287_NAOON.jpg",
        "large": "https://lain.bgm.tv/pic/cover/l/72/2e/37287_NAOON.jpg",
        "medium": "https://lain.bgm.tv/r/800/pic/cover/l/72/2e/37287_NAOON.jpg",
        "common": "https://lain.bgm.tv/r/400/pic/cover/l/72/2e/37287_NAOON.jpg"
      },
      "summary": "　　エドン国は周辺51星を平定した星間国家である。エドン国の王位継承者は、16歳になるまでにすべての領地（同盟星）をめぐる視察の旅に出る義務があった。\r\n　　城での堅苦しい生活が嫌いな王子エドワード・ミトはこのしきたりに従い、身分を隠しての星巡りに大喜びで出発する。 旅の道連れは教育係のスケードと武術指南役のカークスの側近二人。\r\n　　一見平和に見えた諸国だが、見せかけの平和の裏ではそれぞれの為政者による悪事が横行していた。\r\n　　ミト王子は合体ロボ・ダイオージャを駆り、領民を苦しめる悪人どもを成敗していく。",
      "name": "最強ロボ ダイオージャ",
      "name_cn": "最强机器人大王者",
      "tags": [
        {
          "name": "1981",
          "count": 7
        },
        {
          "name": "日本动画",
          "count": 4
        },
        {
          "name": "SUNRISE",
          "count": 4
        },
        {
          "name": "石丸博也",
          "count": 3
        },
        {
          "name": "佐々木勝利",
          "count": 2
        },
        {
          "name": "ロボットアニメ",
          "count": 2
        },
        {
          "name": "古川登志夫",
          "count": 2
        },
        {
          "name": "80",
          "count": 2
        },
        {
          "name": "星山博之",
          "count": 2
        },
        {
          "name": "サンライズ",
          "count": 2
        },
        {
          "name": "TVA",
          "count": 2
        },
        {
          "name": "机甲",
          "count": 2
        },
        {
          "name": "渡辺宙明",
          "count": 1
        },
        {
          "name": "无排名",
          "count": 1
        },
        {
          "name": "1981年1月",
          "count": 1
        },
        {
          "name": "科幻",
          "count": 1
        },
        {
          "name": "伊東恒久",
          "count": 1
        },
        {
          "name": "机器人",
          "count": 1
        },
        {
          "name": "TV动画",
          "count": 1
        },
        {
          "name": "TV",
          "count": 1
        },
        {
          "name": "robo",
          "count": 1
        }
      ],
      "infobox": [
        {
          "key": "中文名",
          "value": "最强机器人大王者"
        },
        {
          "key": "别名",
          "value": [
            {
              "v": "最强机器大王者"
            }
          ]
        },
        {
          "key": "话数",
          "value": "50"
        },
        {
          "key": "放送开始",
          "value": "1981年1月31日"
        },
        {
          "key": "官方网站",
          "value": "https://www.sunrise-inc.co.jp/daioja/index.html"
        },
        {
          "key": "播放结束",
          "value": "1982年1月30日"
        },
        {
          "key": "原作",
          "value": "矢立肇"
        },
        {
          "key": "監督",
          "value": "佐々木勝利"
        },
        {
          "key": "シリーズ構成",
          "value": "星山博之"
        },
        {
          "key": "キャラクターデザイン",
          "value": "佐々門信芳"
        },
        {
          "key": "メカニックデザイン",
          "value": "大河原邦男、出渕裕"
        },
        {
          "key": "音楽",
          "value": "渡辺宙明"
        },
        {
          "key": "製作",
          "value": "名古屋テレビ、創通エージェンシー（現・創通）、日本サンライズ"
        }
      ],
      "rating": {
        "rank": 0,
        "total": 8,
        "count": {
          "1": 0,
          "2": 0,
          "3": 0,
          "4": 0,
          "5": 0,
          "6": 3,
          "7": 5,
          "8": 0,
          "9": 0,
          "10": 0
        },
        "score": 6.6
      },
      "total_episodes": 50,
      "collection": {
        "on_hold": 4,
        "dropped": 6,
        "wish": 16,
        "collect": 13,
        "doing": 3
      },
      "id": 37287,
      "eps": 50,
      "volumes": 0,
      "locked": false,
      "nsfw": false,
      "type": 2,
      "relations": [
        {
          "images": {
            "small": "https://lain.bgm.tv/r/200/pic/cover/l/69/db/208857_jjJjv.jpg",
            "grid": "https://lain.bgm.tv/r/100/pic/cover/l/69/db/208857_jjJjv.jpg",
            "large": "https://lain.bgm.tv/pic/cover/l/69/db/208857_jjJjv.jpg",
            "medium": "https://lain.bgm.tv/r/800/pic/cover/l/69/db/208857_jjJjv.jpg",
            "common": "https://lain.bgm.tv/r/400/pic/cover/l/69/db/208857_jjJjv.jpg"
          },
          "name": "スーパーロボット大戦GC",
          "name_cn": "超级机器人大战GC",
          "relation": "游戏",
          "type": 4,
          "id": 208857
        },
        {
          "images": {
            "small": "https://lain.bgm.tv/r/200/pic/cover/l/40/da/208858_9v8v2.jpg",
            "grid": "https://lain.bgm.tv/r/100/pic/cover/l/40/da/208858_9v8v2.jpg",
            "large": "https://lain.bgm.tv/pic/cover/l/40/da/208858_9v8v2.jpg",
            "medium": "https://lain.bgm.tv/r/800/pic/cover/l/40/da/208858_9v8v2.jpg",
            "common": "https://lain.bgm.tv/r/400/pic/cover/l/40/da/208858_9v8v2.jpg"
          },
          "name": "スーパーロボット大戦XO",
          "name_cn": "超级机器人大战XO",
          "relation": "游戏",
          "type": 4,
          "id": 208858
        }
      ]
    }
  }
]