[
  {
    "title": "ぼくらの七日間戦争",
    "date": "1988-08-13",
    "bangumi": {
      "id": "292740"
    },
    "tmdb": {
      "id": 67907,
      "type": "movie",
      "search": {
        "backdrop_path": "/nkuBlRrKLUEocNDv3kSfvMDOOrG.jpg",
        "id": 67907,
        "original_title": "ぼくらの七日間戦争",
        "overview": "　　改编自宗田理同名小说。\r 　　青叶中学是一所教学严谨的学校，老师只重成绩。八代（佐野史郎 饰）和酒井老师（仓田保昭 饰）对学生轻则斥责，重则体罚，孩子们被压得苦不堪言。\r 　　一天，以菊地英治（菊池健一郎 饰）为首的8名初一男生集体旷课，来到自卫队的废弃兵工厂，将这里命名为“解放区”。不久后中山瞳（宫泽理惠 饰）和另外两名女孩也加入其中，展开了和学校的对抗。\r 　　习惯学生们服从命令的老师们恼羞成怒，和孩子的家长来到兵工厂，软硬兼施，企图进入这里，但都被孩子们用各种方法赶了出去。双方对抗升级，老师们找来了机动部队，孩子们竟发现了一辆坦克！\r 　　他们的抗争能否成功？",
        "poster_path": "/q28XHKT1bS1n0vAgppgl9kX58CX.jpg",
        "media_type": "movie",
        "adult": false,
        "title": "疯狂翘课之七日大作战",
        "original_language": "ja",
        "genre_ids": [
          28,
          35,
          18
        ],
        "release_date": "1988-08-13",
        "video": false
      }
    }
  }
]